h4_hello/__init__.py
h4_hello/__main__.py
h4_hello/_core.py
h4_hello-0.1.14.dist-info/WHEEL
h4_hello-0.1.14.dist-info/entry_points.txt
h4_hello-0.1.14.dist-info/METADATA
h4_hello-0.1.14.dist-info/RECORD
