Metadata-Version: 2.3
Name: h4-hello
Version: 0.1.14
Summary: A simple hello world example
Keywords: demo,hello
Author: heiwa4126
Author-email: heiwa4126 <heiwa4126@gmail.com>
License: MIT License
Classifier: License :: OSI Approved :: MIT License
Classifier: Operating System :: OS Independent
Classifier: Programming Language :: Python :: 3
Requires-Python: >=3.10
Project-URL: Documentation, https://github.com/heiwa4126/h4-hello#readme
Project-URL: Issues, https://github.com/heiwa4126/h4-hello/issues
Project-URL: Source, https://github.com/heiwa4126/h4-hello
